{
    "id": "d7131f47-a962-4832-ae68-52a57bb0b684",
    "url": "https://ll.thespacedevs.com/2.2.0/launch/d7131f47-a962-4832-ae68-52a57bb0b684/",
    "slug": "ceres-1-7-satellites",
    "name": "Ceres-1 | 7 satellites",
    "status": {
        "id": 3,
        "name": "Launch Successful",
        "abbrev": "Success",
        "description": "The launch vehicle successfully inserted its payload(s) into the target orbit(s)."
    },
    "last_updated": "2023-08-10T04:43:23Z",
    "net": "2023-08-10T04:03:50Z",
    "net_precision": {
        "id": 0,
        "name": "Second",
        "abbrev": "SEC",
        "description": "The T-0 is accurate to the second."
    },
    "window_end": "2023-08-10T08:00:00Z",
    "window_start": "2023-08-10T03:00:00Z",
    "lsp_name": "Galactic Energy",
    "mission": "7 satellites",
    "mission_type": "Earth Science",
    "pad": "Launch Area 95A",
    "location": "Jiuquan Satellite Launch Center, People's Republic of China",
    "landing": null,
    "landing_success": null,
    "launcher": null,
    "orbit": "SSO",
    "image": "https://spacelaunchnow-prod-east.nyc3.digitaloceanspaces.com/media/launcher_images/ceres-1_image_20230722081939.jpeg",
    "infographic": null
}